AUTHORS
LICENSE
MANIFEST.in
README.md
requirements.txt
setup.cfg
setup.py
dexplorer/__init__.py
dexplorer/app.py
dexplorer/settings.py
dexplorer.egg-info/PKG-INFO
dexplorer.egg-info/SOURCES.txt
dexplorer.egg-info/dependency_links.txt
dexplorer.egg-info/entry_points.txt
dexplorer.egg-info/requires.txt
dexplorer.egg-info/top_level.txt
dexplorer/extensions/__init__.py
dexplorer/handlers/__init__.py
dexplorer/handlers/views/__init__.py
dexplorer/handlers/views/base.py
dexplorer/handlers/views/plots.py
dexplorer/handlers/views/table.py
dexplorer/handlers/views/utils.py
dexplorer/static/css/bootstrap.min.css
dexplorer/static/css/ie10-viewport-bug-workaround.css
dexplorer/static/css/template.css
dexplorer/static/fonts/glyphicons-halflings-regular.eot
dexplorer/static/fonts/glyphicons-halflings-regular.svg
dexplorer/static/fonts/glyphicons-halflings-regular.ttf
dexplorer/static/fonts/glyphicons-halflings-regular.woff
dexplorer/static/fonts/glyphicons-halflings-regular.woff2
dexplorer/static/img/demo.png
dexplorer/static/img/spin.svg
dexplorer/static/js/angular.min.js
dexplorer/static/js/app.js
dexplorer/static/js/bootstrap.min.js
dexplorer/static/js/d3.v3.min.js
dexplorer/static/js/ie-emulation-modes-warning.js
dexplorer/static/js/jquery-3.1.1.min.js
dexplorer/static/js/mpld3.v0.3.js
dexplorer/templates/index.html
dexplorer/utils/__init__.py
tests/__init__.py
tests/functests.py