Metadata-Version: 1.1
Name: dexplorer
Version: 0.1.1rc0
Summary: View, summarize and visualize data in the browser
Home-page: https://github.com/epigos/data-explorer
Author: Philip Adzanoukpe
Author-email: epigos@gmail.com
License: MIT License
Platform: UNKNOWN
Classifier: Intended Audience :: Developers
Classifier: License :: OSI Approved :: MIT License
Classifier: Programming Language :: Python :: 3.5
Classifier: Topic :: Software Development :: Libraries :: Application Frameworks
Classifier: Topic :: Software Development :: Libraries :: Python Modules
